pysurge/__init__.py
pysurge/__main__.py
pysurge/config.py
pysurge/pysurge.py
pysurge-1.0.1.dist-info/LICENSE
pysurge-1.0.1.dist-info/METADATA
pysurge-1.0.1.dist-info/WHEEL
pysurge-1.0.1.dist-info/entry_points.txt
pysurge-1.0.1.dist-info/top_level.txt
pysurge-1.0.1.dist-info/RECORD
