Metadata-Version: 2.1
Name: pysurge
Version: 1.0.1
Summary: Write small-scale load tests quickly and easily in python with pysurge
Home-page: https://www.github.com/bsquizz/pysurge
Author: Brandon Squizzato
Author-email: bsquizza@redhat.com
License: MIT
Keywords: performance,load,testing,test,qa
Platform: UNKNOWN
Classifier: Topic :: Utilities
Classifier: License :: OSI Approved :: MIT License
Classifier: Programming Language :: Python
Classifier: Programming Language :: Python :: 3.6
Requires-Python: >=3.6
Requires-Dist: pyyaml
Requires-Dist: click
